cdd_tooling/__init__.py
cdd_tooling/assertions.py
cdd_tooling/cli.py
cdd_tooling/coverage.py
cdd_tooling/globbing.py
cdd_tooling/jsonpath.py
cdd_tooling/runner.py
cdd_tooling/analyze/__init__.py
cdd_tooling/analyze/html.py
cdd_tooling/analyze/pdf.py
cdd_tooling/analyze/source.py
cdd_tooling/executors/__init__.py
cdd_tooling/executors/base.py
cdd_tooling/executors/python_exec.py
cdd_tooling/executors/registry.py
cdd_tooling/executors/sclang_exec.py
cdd_tooling/executors/shell_exec.py
cdd_tooling/executors/static_exec.py
cdd_tooling/isolate/__init__.py
cdd_tooling/lint/__init__.py
cdd_tooling/paths/__init__.py
cdd_tooling/spec/__init__.py
cdd_tooling/test/__init__.py
cdd_tooling/spec/SPEC.md
cdd_tooling-0.1.5.dist-info/METADATA
cdd_tooling-0.1.5.dist-info/WHEEL
cdd_tooling-0.1.5.dist-info/entry_points.txt
cdd_tooling-0.1.5.dist-info/RECORD
