Metadata-Version: 2.4
Name: cdd-tooling
Version: 0.1.5
Summary: Reference implementation of Contract-Driven Development tooling
Project-URL: Homepage, https://github.com/thegdyne/cdd-tooling
Project-URL: Documentation, https://github.com/thegdyne/cdd
Author: Gareth Dyne
License: MIT
Keywords: cdd,contracts,testing,tooling,validation
Requires-Python: >=3.10
Requires-Dist: jsonschema>=4.22.0
Requires-Dist: pyyaml>=6.0.1
Requires-Dist: referencing>=0.35.1
Requires-Dist: rich>=13.7.1
Provides-Extra: dev
Requires-Dist: mypy>=1.11.0; extra == 'dev'
Requires-Dist: pytest>=8.2.0; extra == 'dev'
Requires-Dist: ruff>=0.6.0; extra == 'dev'
Provides-Extra: pdf
Requires-Dist: pymupdf>=1.23.0; extra == 'pdf'
Provides-Extra: sclang
